{"pre_post_threshold_time_utc": 1593021600, "image_sprite_url": "https://raw.githubusercontent.com/earnbros/earnbros.github.io/master/api/images/earnings/daily/06-24-2020.png", "json_sprite": {"frames": [{"filename": "BB.png", "frame": {"x": 0, "y": 0, "w": 128, "h": 128}, "rotated": false, "trimmed": false, "spriteSourceSize": {"x": 0, "y": 0, "w": 128, "h": 128}, "sourceSize": {"w": 128, "h": 128}, "pivot": {"x": 0.5, "y": 0.5}}, {"filename": "CPRI.png", "frame": {"x": 128, "y": 0, "w": 128, "h": 128}, "rotated": false, "trimmed": false, "spriteSourceSize": {"x": 0, "y": 0, "w": 128, "h": 128}, "sourceSize": {"w": 128, "h": 128}, "pivot": {"x": 0.5, "y": 0.5}}, {"filename": "LK.png", "frame": {"x": 256, "y": 0, "w": 128, "h": 128}, "rotated": false, "trimmed": false, "spriteSourceSize": {"x": 0, "y": 0, "w": 128, "h": 128}, "sourceSize": {"w": 128, "h": 128}, "pivot": {"x": 0.5, "y": 0.5}}, {"filename": "PAYX.png", "frame": {"x": 384, "y": 0, "w": 128, "h": 128}, "rotated": false, "trimmed": false, "spriteSourceSize": {"x": 0, "y": 0, "w": 128, "h": 128}, "sourceSize": {"w": 128, "h": 128}, "pivot": {"x": 0.5, "y": 0.5}}, {"filename": "SFTBY.png", "frame": {"x": 512, "y": 0, "w": 128, "h": 128}, "rotated": false, "trimmed": false, "spriteSourceSize": {"x": 0, "y": 0, "w": 128, "h": 128}, "sourceSize": {"w": 128, "h": 128}, "pivot": {"x": 0.5, "y": 0.5}}, {"filename": "HCR.png", "frame": {"x": 640, "y": 0, "w": 128, "h": 128}, "rotated": false, "trimmed": false, "spriteSourceSize": {"x": 0, "y": 0, "w": 128, "h": 128}, "sourceSize": {"w": 128, "h": 128}, "pivot": {"x": 0.5, "y": 0.5}}, {"filename": "NG.png", "frame": {"x": 768, "y": 0, "w": 128, "h": 128}, "rotated": false, "trimmed": false, "spriteSourceSize": {"x": 0, "y": 0, "w": 128, "h": 128}, "sourceSize": {"w": 128, "h": 128}, "pivot": {"x": 0.5, "y": 0.5}}, {"filename": "KBH.png", "frame": {"x": 896, "y": 0, "w": 128, "h": 128}, "rotated": false, "trimmed": false, "spriteSourceSize": {"x": 0, "y": 0, "w": 128, "h": 128}, "sourceSize": {"w": 128, "h": 128}, "pivot": {"x": 0.5, "y": 0.5}}, {"filename": "WTI.png", "frame": {"x": 1024, "y": 0, "w": 128, "h": 128}, "rotated": false, "trimmed": false, "spriteSourceSize": {"x": 0, "y": 0, "w": 128, "h": 128}, "sourceSize": {"w": 128, "h": 128}, "pivot": {"x": 0.5, "y": 0.5}}, {"filename": "CRC.png", "frame": {"x": 1152, "y": 0, "w": 128, "h": 128}, "rotated": false, "trimmed": false, "spriteSourceSize": {"x": 0, "y": 0, "w": 128, "h": 128}, "sourceSize": {"w": 128, "h": 128}, "pivot": {"x": 0.5, "y": 0.5}}, {"filename": "FORD.png", "frame": {"x": 1280, "y": 0, "w": 128, "h": 128}, "rotated": false, "trimmed": false, "spriteSourceSize": {"x": 0, "y": 0, "w": 128, "h": 128}, "sourceSize": {"w": 128, "h": 128}, "pivot": {"x": 0.5, "y": 0.5}}, {"filename": "FIZZ.png", "frame": {"x": 1408, "y": 0, "w": 128, "h": 128}, "rotated": false, "trimmed": false, "spriteSourceSize": {"x": 0, "y": 0, "w": 128, "h": 128}, "sourceSize": {"w": 128, "h": 128}, "pivot": {"x": 0.5, "y": 0.5}}, {"filename": "CORR.png", "frame": {"x": 1536, "y": 0, "w": 128, "h": 128}, "rotated": false, "trimmed": false, "spriteSourceSize": {"x": 0, "y": 0, "w": 128, "h": 128}, "sourceSize": {"w": 128, "h": 128}, "pivot": {"x": 0.5, "y": 0.5}}, {"filename": "NNVC.png", "frame": {"x": 1664, "y": 0, "w": 128, "h": 128}, "rotated": false, "trimmed": false, "spriteSourceSize": {"x": 0, "y": 0, "w": 128, "h": 128}, "sourceSize": {"w": 128, "h": 128}, "pivot": {"x": 0.5, "y": 0.5}}, {"filename": "WGO.png", "frame": {"x": 1792, "y": 0, "w": 128, "h": 128}, "rotated": false, "trimmed": false, "spriteSourceSize": {"x": 0, "y": 0, "w": 128, "h": 128}, "sourceSize": {"w": 128, "h": 128}, "pivot": {"x": 0.5, "y": 0.5}}, {"filename": "ACST.png", "frame": {"x": 1920, "y": 0, "w": 128, "h": 128}, "rotated": false, "trimmed": false, "spriteSourceSize": {"x": 0, "y": 0, "w": 128, "h": 128}, "sourceSize": {"w": 128, "h": 128}, "pivot": {"x": 0.5, "y": 0.5}}, {"filename": "ROYT.png", "frame": {"x": 2048, "y": 0, "w": 128, "h": 128}, "rotated": false, "trimmed": false, "spriteSourceSize": {"x": 0, "y": 0, "w": 128, "h": 128}, "sourceSize": {"w": 128, "h": 128}, "pivot": {"x": 0.5, "y": 0.5}}, {"filename": "GLNCY.png", "frame": {"x": 2176, "y": 0, "w": 128, "h": 128}, "rotated": false, "trimmed": false, "spriteSourceSize": {"x": 0, "y": 0, "w": 128, "h": 128}, "sourceSize": {"w": 128, "h": 128}, "pivot": {"x": 0.5, "y": 0.5}}, {"filename": "MATN.png", "frame": {"x": 2304, "y": 0, "w": 128, "h": 128}, "rotated": false, "trimmed": false, "spriteSourceSize": {"x": 0, "y": 0, "w": 128, "h": 128}, "sourceSize": {"w": 128, "h": 128}, "pivot": {"x": 0.5, "y": 0.5}}, {"filename": "CJREF.png", "frame": {"x": 2432, "y": 0, "w": 128, "h": 128}, "rotated": false, "trimmed": false, "spriteSourceSize": {"x": 0, "y": 0, "w": 128, "h": 128}, "sourceSize": {"w": 128, "h": 128}, "pivot": {"x": 0.5, "y": 0.5}}, {"filename": "SMRT.png", "frame": {"x": 2560, "y": 0, "w": 128, "h": 128}, "rotated": false, "trimmed": false, "spriteSourceSize": {"x": 0, "y": 0, "w": 128, "h": 128}, "sourceSize": {"w": 128, "h": 128}, "pivot": {"x": 0.5, "y": 0.5}}, {"filename": "JVA.png", "frame": {"x": 2688, "y": 0, "w": 128, "h": 128}, "rotated": false, "trimmed": false, "spriteSourceSize": {"x": 0, "y": 0, "w": 128, "h": 128}, "sourceSize": {"w": 128, "h": 128}, "pivot": {"x": 0.5, "y": 0.5}}, {"filename": "SOHO.png", "frame": {"x": 2816, "y": 0, "w": 128, "h": 128}, "rotated": false, "trimmed": false, "spriteSourceSize": {"x": 0, "y": 0, "w": 128, "h": 128}, "sourceSize": {"w": 128, "h": 128}, "pivot": {"x": 0.5, "y": 0.5}}, {"filename": "SCHN.png", "frame": {"x": 2944, "y": 0, "w": 128, "h": 128}, "rotated": false, "trimmed": false, "spriteSourceSize": {"x": 0, "y": 0, "w": 128, "h": 128}, "sourceSize": {"w": 128, "h": 128}, "pivot": {"x": 0.5, "y": 0.5}}, {"filename": "RAVE.png", "frame": {"x": 3072, "y": 0, "w": 128, "h": 128}, "rotated": false, "trimmed": false, "spriteSourceSize": {"x": 0, "y": 0, "w": 128, "h": 128}, "sourceSize": {"w": 128, "h": 128}, "pivot": {"x": 0.5, "y": 0.5}}, {"filename": "SINO.png", "frame": {"x": 3200, "y": 0, "w": 128, "h": 128}, "rotated": false, "trimmed": false, "spriteSourceSize": {"x": 0, "y": 0, "w": 128, "h": 128}, "sourceSize": {"w": 128, "h": 128}, "pivot": {"x": 0.5, "y": 0.5}}, {"filename": "SMMT.png", "frame": {"x": 3328, "y": 0, "w": 128, "h": 128}, "rotated": false, "trimmed": false, "spriteSourceSize": {"x": 0, "y": 0, "w": 128, "h": 128}, "sourceSize": {"w": 128, "h": 128}, "pivot": {"x": 0.5, "y": 0.5}}, {"filename": "VEND.png", "frame": {"x": 3456, "y": 0, "w": 128, "h": 128}, "rotated": false, "trimmed": false, "spriteSourceSize": {"x": 0, "y": 0, "w": 128, "h": 128}, "sourceSize": {"w": 128, "h": 128}, "pivot": {"x": 0.5, "y": 0.5}}, {"filename": "FUL.png", "frame": {"x": 3584, "y": 0, "w": 128, "h": 128}, "rotated": false, "trimmed": false, "spriteSourceSize": {"x": 0, "y": 0, "w": 128, "h": 128}, "sourceSize": {"w": 128, "h": 128}, "pivot": {"x": 0.5, "y": 0.5}}, {"filename": "TRPX.png", "frame": {"x": 3712, "y": 0, "w": 128, "h": 128}, "rotated": false, "trimmed": false, "spriteSourceSize": {"x": 0, "y": 0, "w": 128, "h": 128}, "sourceSize": {"w": 128, "h": 128}, "pivot": {"x": 0.5, "y": 0.5}}, {"filename": "KGJI.png", "frame": {"x": 3840, "y": 0, "w": 128, "h": 128}, "rotated": false, "trimmed": false, "spriteSourceSize": {"x": 0, "y": 0, "w": 128, "h": 128}, "sourceSize": {"w": 128, "h": 128}, "pivot": {"x": 0.5, "y": 0.5}}, {"filename": "SOUHY.png", "frame": {"x": 3968, "y": 0, "w": 128, "h": 128}, "rotated": false, "trimmed": false, "spriteSourceSize": {"x": 0, "y": 0, "w": 128, "h": 128}, "sourceSize": {"w": 128, "h": 128}, "pivot": {"x": 0.5, "y": 0.5}}, {"filename": "ATRX.png", "frame": {"x": 4096, "y": 0, "w": 128, "h": 128}, "rotated": false, "trimmed": false, "spriteSourceSize": {"x": 0, "y": 0, "w": 128, "h": 128}, "sourceSize": {"w": 128, "h": 128}, "pivot": {"x": 0.5, "y": 0.5}}, {"filename": "KKPNF.png", "frame": {"x": 4224, "y": 0, "w": 128, "h": 128}, "rotated": false, "trimmed": false, "spriteSourceSize": {"x": 0, "y": 0, "w": 128, "h": 128}, "sourceSize": {"w": 128, "h": 128}, "pivot": {"x": 0.5, "y": 0.5}}, {"filename": "HBB.png", "frame": {"x": 4352, "y": 0, "w": 128, "h": 128}, "rotated": false, "trimmed": false, "spriteSourceSize": {"x": 0, "y": 0, "w": 128, "h": 128}, "sourceSize": {"w": 128, "h": 128}, "pivot": {"x": 0.5, "y": 0.5}}, {"filename": "GNBT.png", "frame": {"x": 4480, "y": 0, "w": 128, "h": 128}, "rotated": false, "trimmed": false, "spriteSourceSize": {"x": 0, "y": 0, "w": 128, "h": 128}, "sourceSize": {"w": 128, "h": 128}, "pivot": {"x": 0.5, "y": 0.5}}, {"filename": "HIPH.png", "frame": {"x": 4608, "y": 0, "w": 128, "h": 128}, "rotated": false, "trimmed": false, "spriteSourceSize": {"x": 0, "y": 0, "w": 128, "h": 128}, "sourceSize": {"w": 128, "h": 128}, "pivot": {"x": 0.5, "y": 0.5}}, {"filename": "POLA.png", "frame": {"x": 4736, "y": 0, "w": 128, "h": 128}, "rotated": false, "trimmed": false, "spriteSourceSize": {"x": 0, "y": 0, "w": 128, "h": 128}, "sourceSize": {"w": 128, "h": 128}, "pivot": {"x": 0.5, "y": 0.5}}, {"filename": "SGSI.png", "frame": {"x": 4864, "y": 0, "w": 128, "h": 128}, "rotated": false, "trimmed": false, "spriteSourceSize": {"x": 0, "y": 0, "w": 128, "h": 128}, "sourceSize": {"w": 128, "h": 128}, "pivot": {"x": 0.5, "y": 0.5}}, {"filename": "HALL.png", "frame": {"x": 4992, "y": 0, "w": 128, "h": 128}, "rotated": false, "trimmed": false, "spriteSourceSize": {"x": 0, "y": 0, "w": 128, "h": 128}, "sourceSize": {"w": 128, "h": 128}, "pivot": {"x": 0.5, "y": 0.5}}, {"filename": "PBIO.png", "frame": {"x": 5120, "y": 0, "w": 128, "h": 128}, "rotated": false, "trimmed": false, "spriteSourceSize": {"x": 0, "y": 0, "w": 128, "h": 128}, "sourceSize": {"w": 128, "h": 128}, "pivot": {"x": 0.5, "y": 0.5}}, {"filename": "CULP.png", "frame": {"x": 5248, "y": 0, "w": 128, "h": 128}, "rotated": false, "trimmed": false, "spriteSourceSize": {"x": 0, "y": 0, "w": 128, "h": 128}, "sourceSize": {"w": 128, "h": 128}, "pivot": {"x": 0.5, "y": 0.5}}, {"filename": "SGMA.png", "frame": {"x": 5376, "y": 0, "w": 128, "h": 128}, "rotated": false, "trimmed": false, "spriteSourceSize": {"x": 0, "y": 0, "w": 128, "h": 128}, "sourceSize": {"w": 128, "h": 128}, "pivot": {"x": 0.5, "y": 0.5}}, {"filename": "BDL.png", "frame": {"x": 5504, "y": 0, "w": 128, "h": 128}, "rotated": false, "trimmed": false, "spriteSourceSize": {"x": 0, "y": 0, "w": 128, "h": 128}, "sourceSize": {"w": 128, "h": 128}, "pivot": {"x": 0.5, "y": 0.5}}, {"filename": "QMCO.png", "frame": {"x": 5632, "y": 0, "w": 128, "h": 128}, "rotated": false, "trimmed": false, "spriteSourceSize": {"x": 0, "y": 0, "w": 128, "h": 128}, "sourceSize": {"w": 128, "h": 128}, "pivot": {"x": 0.5, "y": 0.5}}, {"filename": "HLUYY.png", "frame": {"x": 5760, "y": 0, "w": 128, "h": 128}, "rotated": false, "trimmed": false, "spriteSourceSize": {"x": 0, "y": 0, "w": 128, "h": 128}, "sourceSize": {"w": 128, "h": 128}, "pivot": {"x": 0.5, "y": 0.5}}, {"filename": "CARV.png", "frame": {"x": 5888, "y": 0, "w": 128, "h": 128}, "rotated": false, "trimmed": false, "spriteSourceSize": {"x": 0, "y": 0, "w": 128, "h": 128}, "sourceSize": {"w": 128, "h": 128}, "pivot": {"x": 0.5, "y": 0.5}}, {"filename": "RPMT.png", "frame": {"x": 6016, "y": 0, "w": 128, "h": 128}, "rotated": false, "trimmed": false, "spriteSourceSize": {"x": 0, "y": 0, "w": 128, "h": 128}, "sourceSize": {"w": 128, "h": 128}, "pivot": {"x": 0.5, "y": 0.5}}, {"filename": "MEEC.png", "frame": {"x": 6144, "y": 0, "w": 128, "h": 128}, "rotated": false, "trimmed": false, "spriteSourceSize": {"x": 0, "y": 0, "w": 128, "h": 128}, "sourceSize": {"w": 128, "h": 128}, "pivot": {"x": 0.5, "y": 0.5}}, {"filename": "DLPN.png", "frame": {"x": 6272, "y": 0, "w": 128, "h": 128}, "rotated": false, "trimmed": false, "spriteSourceSize": {"x": 0, "y": 0, "w": 128, "h": 128}, "sourceSize": {"w": 128, "h": 128}, "pivot": {"x": 0.5, "y": 0.5}}, {"filename": "GLXZ.png", "frame": {"x": 6400, "y": 0, "w": 128, "h": 128}, "rotated": false, "trimmed": false, "spriteSourceSize": {"x": 0, "y": 0, "w": 128, "h": 128}, "sourceSize": {"w": 128, "h": 128}, "pivot": {"x": 0.5, "y": 0.5}}, {"filename": "AMNL.png", "frame": {"x": 6528, "y": 0, "w": 128, "h": 128}, "rotated": false, "trimmed": false, "spriteSourceSize": {"x": 0, "y": 0, "w": 128, "h": 128}, "sourceSize": {"w": 128, "h": 128}, "pivot": {"x": 0.5, "y": 0.5}}, {"filename": "VCSY.png", "frame": {"x": 6656, "y": 0, "w": 128, "h": 19}, "rotated": false, "trimmed": false, "spriteSourceSize": {"x": 0, "y": 0, "w": 128, "h": 19}, "sourceSize": {"w": 128, "h": 19}, "pivot": {"x": 0.5, "y": 0.5}}, {"filename": "MAKSY.png", "frame": {"x": 6784, "y": 0, "w": 128, "h": 76}, "rotated": false, "trimmed": false, "spriteSourceSize": {"x": 0, "y": 0, "w": 128, "h": 76}, "sourceSize": {"w": 128, "h": 76}, "pivot": {"x": 0.5, "y": 0.5}}, {"filename": "BWAY.png", "frame": {"x": 6912, "y": 0, "w": 128, "h": 128}, "rotated": false, "trimmed": false, "spriteSourceSize": {"x": 0, "y": 0, "w": 128, "h": 128}, "sourceSize": {"w": 128, "h": 128}, "pivot": {"x": 0.5, "y": 0.5}}, {"filename": "EBR.B.png", "frame": {"x": 7040, "y": 0, "w": 128, "h": 128}, "rotated": false, "trimmed": false, "spriteSourceSize": {"x": 0, "y": 0, "w": 128, "h": 128}, "sourceSize": {"w": 128, "h": 128}, "pivot": {"x": 0.5, "y": 0.5}}, {"filename": "ALPP.png", "frame": {"x": 7168, "y": 0, "w": 128, "h": 128}, "rotated": false, "trimmed": false, "spriteSourceSize": {"x": 0, "y": 0, "w": 128, "h": 128}, "sourceSize": {"w": 128, "h": 128}, "pivot": {"x": 0.5, "y": 0.5}}, {"filename": "SENR.png", "frame": {"x": 7296, "y": 0, "w": 128, "h": 128}, "rotated": false, "trimmed": false, "spriteSourceSize": {"x": 0, "y": 0, "w": 128, "h": 128}, "sourceSize": {"w": 128, "h": 128}, "pivot": {"x": 0.5, "y": 0.5}}, {"filename": "ALPE.png", "frame": {"x": 7424, "y": 0, "w": 128, "h": 128}, "rotated": false, "trimmed": false, "spriteSourceSize": {"x": 0, "y": 0, "w": 128, "h": 128}, "sourceSize": {"w": 128, "h": 128}, "pivot": {"x": 0.5, "y": 0.5}}, {"filename": "BNET.png", "frame": {"x": 7552, "y": 0, "w": 128, "h": 128}, "rotated": false, "trimmed": false, "spriteSourceSize": {"x": 0, "y": 0, "w": 128, "h": 128}, "sourceSize": {"w": 128, "h": 128}, "pivot": {"x": 0.5, "y": 0.5}}, {"filename": "ADMT.png", "frame": {"x": 7680, "y": 0, "w": 128, "h": 128}, "rotated": false, "trimmed": false, "spriteSourceSize": {"x": 0, "y": 0, "w": 128, "h": 128}, "sourceSize": {"w": 128, "h": 128}, "pivot": {"x": 0.5, "y": 0.5}}, {"filename": "ELLO.png", "frame": {"x": 7808, "y": 0, "w": 128, "h": 128}, "rotated": false, "trimmed": false, "spriteSourceSize": {"x": 0, "y": 0, "w": 128, "h": 128}, "sourceSize": {"w": 128, "h": 128}, "pivot": {"x": 0.5, "y": 0.5}}, {"filename": "AHCHY.png", "frame": {"x": 7936, "y": 0, "w": 128, "h": 128}, "rotated": false, "trimmed": false, "spriteSourceSize": {"x": 0, "y": 0, "w": 128, "h": 128}, "sourceSize": {"w": 128, "h": 128}, "pivot": {"x": 0.5, "y": 0.5}}, {"filename": "DWOG.png", "frame": {"x": 8064, "y": 0, "w": 128, "h": 128}, "rotated": false, "trimmed": false, "spriteSourceSize": {"x": 0, "y": 0, "w": 128, "h": 128}, "sourceSize": {"w": 128, "h": 128}, "pivot": {"x": 0.5, "y": 0.5}}, {"filename": "GRST.png", "frame": {"x": 8192, "y": 0, "w": 128, "h": 128}, "rotated": false, "trimmed": false, "spriteSourceSize": {"x": 0, "y": 0, "w": 128, "h": 128}, "sourceSize": {"w": 128, "h": 128}, "pivot": {"x": 0.5, "y": 0.5}}, {"filename": "KXIN.png", "frame": {"x": 8320, "y": 0, "w": 128, "h": 128}, "rotated": false, "trimmed": false, "spriteSourceSize": {"x": 0, "y": 0, "w": 128, "h": 128}, "sourceSize": {"w": 128, "h": 128}, "pivot": {"x": 0.5, "y": 0.5}}, {"filename": "MKD.png", "frame": {"x": 8448, "y": 0, "w": 128, "h": 128}, "rotated": false, "trimmed": false, "spriteSourceSize": {"x": 0, "y": 0, "w": 128, "h": 128}, "sourceSize": {"w": 128, "h": 128}, "pivot": {"x": 0.5, "y": 0.5}}, {"filename": "JFBC.png", "frame": {"x": 8576, "y": 0, "w": 128, "h": 128}, "rotated": false, "trimmed": false, "spriteSourceSize": {"x": 0, "y": 0, "w": 128, "h": 128}, "sourceSize": {"w": 128, "h": 128}, "pivot": {"x": 0.5, "y": 0.5}}, {"filename": "INTV.png", "frame": {"x": 8704, "y": 0, "w": 128, "h": 128}, "rotated": false, "trimmed": false, "spriteSourceSize": {"x": 0, "y": 0, "w": 128, "h": 128}, "sourceSize": {"w": 128, "h": 128}, "pivot": {"x": 0.5, "y": 0.5}}, {"filename": "CMPD.png", "frame": {"x": 8832, "y": 0, "w": 128, "h": 128}, "rotated": false, "trimmed": false, "spriteSourceSize": {"x": 0, "y": 0, "w": 128, "h": 128}, "sourceSize": {"w": 128, "h": 128}, "pivot": {"x": 0.5, "y": 0.5}}, {"filename": "IGEN.png", "frame": {"x": 8960, "y": 0, "w": 128, "h": 128}, "rotated": false, "trimmed": false, "spriteSourceSize": {"x": 0, "y": 0, "w": 128, "h": 128}, "sourceSize": {"w": 128, "h": 128}, "pivot": {"x": 0.5, "y": 0.5}}, {"filename": "GMAN.png", "frame": {"x": 9088, "y": 0, "w": 128, "h": 128}, "rotated": false, "trimmed": false, "spriteSourceSize": {"x": 0, "y": 0, "w": 128, "h": 128}, "sourceSize": {"w": 128, "h": 128}, "pivot": {"x": 0.5, "y": 0.5}}, {"filename": "IOCJY.png", "frame": {"x": 9216, "y": 0, "w": 128, "h": 64}, "rotated": false, "trimmed": false, "spriteSourceSize": {"x": 0, "y": 0, "w": 128, "h": 64}, "sourceSize": {"w": 128, "h": 64}, "pivot": {"x": 0.5, "y": 0.5}}, {"filename": "PFTI.png", "frame": {"x": 9344, "y": 0, "w": 128, "h": 128}, "rotated": false, "trimmed": false, "spriteSourceSize": {"x": 0, "y": 0, "w": 128, "h": 128}, "sourceSize": {"w": 128, "h": 128}, "pivot": {"x": 0.5, "y": 0.5}}, {"filename": "AOXY.png", "frame": {"x": 9472, "y": 0, "w": 128, "h": 128}, "rotated": false, "trimmed": false, "spriteSourceSize": {"x": 0, "y": 0, "w": 128, "h": 128}, "sourceSize": {"w": 128, "h": 128}, "pivot": {"x": 0.5, "y": 0.5}}], "meta": {"app": "https://www.codeandweb.com/texturepacker", "version": "1.0", "image": "06-24-2020.png", "format": "RGBA8888", "size": {"w": 9600, "h": 128}, "scale": "1", "smartupdate": ""}}, "companies": [{"market_cap": 2917609575, "industry_name": "Software", "sector_name": "Information Technology", "symbol": "BB", "name": "BlackBerry", "next_earnings_utc": 1593029100, "image_sprite_name": "BB.png", "data_url": "/home/nima/Code/Earnbros/private/earnbros/v1/static/json/companies/BB.json"}, {"market_cap": 2570578482, "industry_name": "Textiles, Apparel and Luxury Goods", "sector_name": "Consumer Discretionary", "symbol": "CPRI", "name": "Capri Holdings", "next_earnings_utc": 1592994600, "image_sprite_name": "CPRI.png", "data_url": "/home/nima/Code/Earnbros/private/earnbros/v1/static/json/companies/CPRI.json"}, {"market_cap": 984741246, "industry_name": "Hotels, Restaurants and Leisure", "sector_name": "Consumer Discretionary", "symbol": "LK", "name": "Luckin Coffee", "next_earnings_utc": 1592992800, "image_sprite_name": "LK.png", "data_url": "/home/nima/Code/Earnbros/private/earnbros/v1/static/json/companies/LK.json"}, {"market_cap": 26458850485, "industry_name": "IT Services", "sector_name": "Information Technology", "symbol": "PAYX", "name": "Paychex", "next_earnings_utc": 1593000900, "image_sprite_name": "PAYX.png", "data_url": "/home/nima/Code/Earnbros/private/earnbros/v1/static/json/companies/PAYX.json"}, {"market_cap": 94503794326, "industry_name": "Wireless Telecommunication Services", "sector_name": "Communication Services", "symbol": "SFTBY", "name": "SoftBank Group", "next_earnings_utc": 1592992800, "image_sprite_name": "SFTBY.png", "data_url": "/home/nima/Code/Earnbros/private/earnbros/v1/static/json/companies/SFTBY.json"}, {"market_cap": 33148354, "industry_name": "Energy Equipment and Services", "sector_name": "Energy", "symbol": "HCR", "name": "Hi-Crush", "next_earnings_utc": 1593033600, "image_sprite_name": "HCR.png", "data_url": "/home/nima/Code/Earnbros/private/earnbros/v1/static/json/companies/HCR.json"}, {"market_cap": 2760346683, "industry_name": "Metals and Mining", "sector_name": "Materials", "symbol": "NG", "name": "NovaGold Resources", "next_earnings_utc": 1593033600, "image_sprite_name": "NG.png", "data_url": "/home/nima/Code/Earnbros/private/earnbros/v1/static/json/companies/NG.json"}, {"market_cap": 2886202955, "industry_name": "Household Durables", "sector_name": "Consumer Discretionary", "symbol": "KBH", "name": "KB Home", "next_earnings_utc": 1593029400, "image_sprite_name": "KBH.png", "data_url": "/home/nima/Code/Earnbros/private/earnbros/v1/static/json/companies/KBH.json"}, {"market_cap": 404820879, "industry_name": "Oil, Gas and Consumable Fuels", "sector_name": "Energy", "symbol": "WTI", "name": "W&T Offshore", "next_earnings_utc": 1593031500, "image_sprite_name": "WTI.png", "data_url": "/home/nima/Code/Earnbros/private/earnbros/v1/static/json/companies/WTI.json"}, {"market_cap": 74531925, "industry_name": "Oil, Gas and Consumable Fuels", "sector_name": "Energy", "symbol": "CRC", "name": "California Resources", "next_earnings_utc": 1593029700, "image_sprite_name": "CRC.png", "data_url": "/home/nima/Code/Earnbros/private/earnbros/v1/static/json/companies/CRC.json"}, {"market_cap": 11631298, "industry_name": "Textiles, Apparel and Luxury Goods", "sector_name": "Consumer Discretionary", "symbol": "FORD", "name": "Forward Industries", "next_earnings_utc": 1593032700, "image_sprite_name": "FORD.png", "data_url": "/home/nima/Code/Earnbros/private/earnbros/v1/static/json/companies/FORD.json"}, {"market_cap": 2658537797, "industry_name": "Beverages", "sector_name": "Consumer Staples", "symbol": "FIZZ", "name": "National Beverage", "next_earnings_utc": 1592992800, "image_sprite_name": "FIZZ.png", "data_url": "/home/nima/Code/Earnbros/private/earnbros/v1/static/json/companies/FIZZ.json"}, {"market_cap": 168732799, "industry_name": "Equity Real Estate Investment Trusts (REITs)", "sector_name": "Real Estate", "symbol": "CORR", "name": "CorEnergy Infrastructure Trust", "next_earnings_utc": 1593032400, "image_sprite_name": "CORR.png", "data_url": "/home/nima/Code/Earnbros/private/earnbros/v1/static/json/companies/CORR.json"}, {"market_cap": 62645216, "industry_name": "Biotechnology", "sector_name": "Health Care", "symbol": "NNVC", "name": "NanoViricides", "next_earnings_utc": 1593007200, "image_sprite_name": "NNVC.png", "data_url": "/home/nima/Code/Earnbros/private/earnbros/v1/static/json/companies/NNVC.json"}, {"market_cap": 2161653248, "industry_name": "Automobiles", "sector_name": "Consumer Discretionary", "symbol": "WGO", "name": "Winnebago Industries", "next_earnings_utc": 1592996400, "image_sprite_name": "WGO.png", "data_url": "/home/nima/Code/Earnbros/private/earnbros/v1/static/json/companies/WGO.json"}, {"market_cap": 64365646, "industry_name": "Pharmaceuticals", "sector_name": "Health Care", "symbol": "ACST", "name": "Acasti Pharma", "next_earnings_utc": 1593000000, "image_sprite_name": "ACST.png", "data_url": "/home/nima/Code/Earnbros/private/earnbros/v1/static/json/companies/ACST.json"}, {"market_cap": 15819094, "industry_name": "Oil, Gas and Consumable Fuels", "sector_name": "Energy", "symbol": "ROYT", "name": "Pacific Coast Oil Trust", "next_earnings_utc": 1593007200, "image_sprite_name": "ROYT.png", "data_url": "/home/nima/Code/Earnbros/private/earnbros/v1/static/json/companies/ROYT.json"}, {"market_cap": 28516774893, "industry_name": "Metals and Mining", "sector_name": "Materials", "symbol": "GLNCY", "name": "Glencore plc", "next_earnings_utc": 1593007200, "image_sprite_name": "GLNCY.png", "data_url": "/home/nima/Code/Earnbros/private/earnbros/v1/static/json/companies/GLNCY.json"}, {"market_cap": null, "industry_name": null, "sector_name": null, "symbol": "MATN", "name": "Mateon Therapeutics", "next_earnings_utc": 1593030600, "image_sprite_name": "MATN.png", "data_url": "/home/nima/Code/Earnbros/private/earnbros/v1/static/json/companies/MATN.json"}, {"market_cap": 574765509, "industry_name": "Media", "sector_name": "Communication Services", "symbol": "CJREF", "name": "Corus Entertainment", "next_earnings_utc": 1592996400, "image_sprite_name": "CJREF.png", "data_url": "/home/nima/Code/Earnbros/private/earnbros/v1/static/json/companies/CJREF.json"}, {"market_cap": 21291658, "industry_name": "Specialty Retail", "sector_name": "Consumer Discretionary", "symbol": "SMRT", "name": "Stein Mart", "next_earnings_utc": 1593029100, "image_sprite_name": "SMRT.png", "data_url": "/home/nima/Code/Earnbros/private/earnbros/v1/static/json/companies/SMRT.json"}, {"market_cap": 16151112, "industry_name": "Food Products", "sector_name": "Consumer Staples", "symbol": "JVA", "name": "Coffee Holding Co.", "next_earnings_utc": 1593004500, "image_sprite_name": "JVA.png", "data_url": "/home/nima/Code/Earnbros/private/earnbros/v1/static/json/companies/JVA.json"}, {"market_cap": 48160822, "industry_name": "Equity Real Estate Investment Trusts (REITs)", "sector_name": "Real Estate", "symbol": "SOHO", "name": "Sotherly Hotels", "next_earnings_utc": 1592994600, "image_sprite_name": "SOHO.png", "data_url": "/home/nima/Code/Earnbros/private/earnbros/v1/static/json/companies/SOHO.json"}, {"market_cap": 458251986, "industry_name": "Metals and Mining", "sector_name": "Materials", "symbol": "SCHN", "name": "Schnitzer Steel Industries", "next_earnings_utc": 1593000000, "image_sprite_name": "SCHN.png", "data_url": "/home/nima/Code/Earnbros/private/earnbros/v1/static/json/companies/SCHN.json"}, {"market_cap": 13036252, "industry_name": "Hotels, Restaurants and Leisure", "sector_name": "Consumer Discretionary", "symbol": "RAVE", "name": "RAVE Restaurant Group", "next_earnings_utc": 1593000000, "image_sprite_name": "RAVE.png", "data_url": "/home/nima/Code/Earnbros/private/earnbros/v1/static/json/companies/RAVE.json"}, {"market_cap": 10131967, "industry_name": "Transportation Infrastructure", "sector_name": "Industrials", "symbol": "SINO", "name": "Sino-Global Shipping America", "next_earnings_utc": 1593007200, "image_sprite_name": "SINO.png", "data_url": "/home/nima/Code/Earnbros/private/earnbros/v1/static/json/companies/SINO.json"}, {"market_cap": 234639337, "industry_name": "Biotechnology", "sector_name": "Health Care", "symbol": "SMMT", "name": "Summit Therapeutics plc", "next_earnings_utc": 1592992800, "image_sprite_name": "SMMT.png", "data_url": "/home/nima/Code/Earnbros/private/earnbros/v1/static/json/companies/SMMT.json"}, {"market_cap": 819557, "industry_name": "Trading Companies and Distributors", "sector_name": "Industrials", "symbol": "VEND", "name": "Generation Next Franchise Brands Inc", "next_earnings_utc": 1593030600, "image_sprite_name": "VEND.png", "data_url": "/home/nima/Code/Earnbros/private/earnbros/v1/static/json/companies/VEND.json"}, {"market_cap": 2056958631, "industry_name": "Chemicals", "sector_name": "Materials", "symbol": "FUL", "name": "H.B. Fuller Company", "next_earnings_utc": 1593029100, "image_sprite_name": "FUL.png", "data_url": "/home/nima/Code/Earnbros/private/earnbros/v1/static/json/companies/FUL.json"}, {"market_cap": 4604358, "industry_name": "Biotechnology", "sector_name": "Health Care", "symbol": "TRPX", "name": "Therapix Biosciences", "next_earnings_utc": 1593001800, "image_sprite_name": "TRPX.png", "data_url": "/home/nima/Code/Earnbros/private/earnbros/v1/static/json/companies/TRPX.json"}, {"market_cap": 11791542, "industry_name": "Textiles, Apparel and Luxury Goods", "sector_name": "Consumer Discretionary", "symbol": "KGJI", "name": "Kingold Jewelry", "next_earnings_utc": 1593030600, "image_sprite_name": "KGJI.png", "data_url": "/home/nima/Code/Earnbros/private/earnbros/v1/static/json/companies/KGJI.json"}, {"market_cap": 6922386923, "industry_name": "Metals and Mining", "sector_name": "Materials", "symbol": "SOUHY", "name": "South32", "next_earnings_utc": 1593007200, "image_sprite_name": "SOUHY.png", "data_url": "/home/nima/Code/Earnbros/private/earnbros/v1/static/json/companies/SOUHY.json"}, {"market_cap": 869562, "industry_name": "Biotechnology", "sector_name": "Health Care", "symbol": "ATRX", "name": "Adhera Therapeutics", "next_earnings_utc": 1592996400, "image_sprite_name": "ATRX.png", "data_url": "/home/nima/Code/Earnbros/private/earnbros/v1/static/json/companies/ATRX.json"}, {"market_cap": 10613667379, "industry_name": "Diversified Telecommunication Services", "sector_name": "Communication Services", "symbol": "KKPNF", "name": "Koninklijke KPN", "next_earnings_utc": 1593007200, "image_sprite_name": "KKPNF.png", "data_url": "/home/nima/Code/Earnbros/private/earnbros/v1/static/json/companies/KKPNF.json"}, {"market_cap": 143610440, "industry_name": "Household Durables", "sector_name": "Consumer Discretionary", "symbol": "HBB", "name": "Hamilton Beach Brands Holding Company", "next_earnings_utc": 1593031500, "image_sprite_name": "HBB.png", "data_url": "/home/nima/Code/Earnbros/private/earnbros/v1/static/json/companies/HBB.json"}, {"market_cap": 49280057, "industry_name": "Biotechnology", "sector_name": "Health Care", "symbol": "GNBT", "name": "Generex Biotechnology", "next_earnings_utc": 1593007200, "image_sprite_name": "GNBT.png", "data_url": "/home/nima/Code/Earnbros/private/earnbros/v1/static/json/companies/GNBT.json"}, {"market_cap": null, "industry_name": "Beverages", "sector_name": "Consumer Staples", "symbol": "HIPH", "name": "American Premium Water", "next_earnings_utc": 1592996400, "image_sprite_name": "HIPH.png", "data_url": "/home/nima/Code/Earnbros/private/earnbros/v1/static/json/companies/HIPH.json"}, {"market_cap": 14580980, "industry_name": "Electrical Equipment", "sector_name": "Industrials", "symbol": "POLA", "name": "Polar Power", "next_earnings_utc": 1593029100, "image_sprite_name": "POLA.png", "data_url": "/home/nima/Code/Earnbros/private/earnbros/v1/static/json/companies/POLA.json"}, {"market_cap": null, "industry_name": null, "sector_name": null, "symbol": "SGSI", "name": "Spectrum Global Solutions", "next_earnings_utc": 1593007200, "image_sprite_name": "SGSI.png", "data_url": "/home/nima/Code/Earnbros/private/earnbros/v1/static/json/companies/SGSI.json"}, {"market_cap": 70317600, "industry_name": "Insurance", "sector_name": "Financials", "symbol": "HALL", "name": "Hallmark Financial Services", "next_earnings_utc": 1593029100, "image_sprite_name": "HALL.png", "data_url": "/home/nima/Code/Earnbros/private/earnbros/v1/static/json/companies/HALL.json"}, {"market_cap": 8396582, "industry_name": "Life Sciences Tools and Services", "sector_name": "Health Care", "symbol": "PBIO", "name": "Pressure BioSciences", "next_earnings_utc": 1593030600, "image_sprite_name": "PBIO.png", "data_url": "/home/nima/Code/Earnbros/private/earnbros/v1/static/json/companies/PBIO.json"}, {"market_cap": 97090772, "industry_name": "Textiles, Apparel and Luxury Goods", "sector_name": "Consumer Discretionary", "symbol": "CULP", "name": "Culp", "next_earnings_utc": 1593029700, "image_sprite_name": "CULP.png", "data_url": "/home/nima/Code/Earnbros/private/earnbros/v1/static/json/companies/CULP.json"}, {"market_cap": 13406325, "industry_name": "Electronic Equipment, Instruments and Components", "sector_name": "Information Technology", "symbol": "SGMA", "name": "SigmaTron International", "next_earnings_utc": 1593007200, "image_sprite_name": "SGMA.png", "data_url": "/home/nima/Code/Earnbros/private/earnbros/v1/static/json/companies/SGMA.json"}, {"market_cap": 29459554, "industry_name": "Hotels, Restaurants and Leisure", "sector_name": "Consumer Discretionary", "symbol": "BDL", "name": "Flanigan's Enterprises", "next_earnings_utc": 1593034500, "image_sprite_name": "BDL.png", "data_url": "/home/nima/Code/Earnbros/private/earnbros/v1/static/json/companies/BDL.json"}, {"market_cap": 163819220, "industry_name": "Technology Hardware, Storage and Peripherals", "sector_name": "Information Technology", "symbol": "QMCO", "name": "Quantum", "next_earnings_utc": 1593029100, "image_sprite_name": "QMCO.png", "data_url": "/home/nima/Code/Earnbros/private/earnbros/v1/static/json/companies/QMCO.json"}, {"market_cap": 7489273963, "industry_name": "Pharmaceuticals", "sector_name": "Health Care", "symbol": "HLUYY", "name": "H. Lundbeck", "next_earnings_utc": 1592992800, "image_sprite_name": "HLUYY.png", "data_url": "/home/nima/Code/Earnbros/private/earnbros/v1/static/json/companies/HLUYY.json"}, {"market_cap": 7362014, "industry_name": "Thrifts and Mortgage Finance", "sector_name": "Financials", "symbol": "CARV", "name": "Carver Bancorp", "next_earnings_utc": 1592996400, "image_sprite_name": "CARV.png", "data_url": "/home/nima/Code/Earnbros/private/earnbros/v1/static/json/companies/CARV.json"}, {"market_cap": 24367861, "industry_name": "IT Services", "sector_name": "Information Technology", "symbol": "RPMT", "name": "Rego Payment Architectures", "next_earnings_utc": 1593007200, "image_sprite_name": "RPMT.png", "data_url": "/home/nima/Code/Earnbros/private/earnbros/v1/static/json/companies/RPMT.json"}, {"market_cap": 14383333, "industry_name": "Commercial Services and Supplies", "sector_name": "Industrials", "symbol": "MEEC", "name": "Midwest Energy Emissions", "next_earnings_utc": 1592992800, "image_sprite_name": "MEEC.png", "data_url": "/home/nima/Code/Earnbros/private/earnbros/v1/static/json/companies/MEEC.json"}, {"market_cap": 17231739, "industry_name": "Entertainment", "sector_name": "Communication Services", "symbol": "DLPN", "name": "Dolphin Entertainment", "next_earnings_utc": 1593030600, "image_sprite_name": "DLPN.png", "data_url": "/home/nima/Code/Earnbros/private/earnbros/v1/static/json/companies/DLPN.json"}, {"market_cap": 19666808, "industry_name": "Hotels, Restaurants and Leisure", "sector_name": "Consumer Discretionary", "symbol": "GLXZ", "name": "Galaxy Gaming", "next_earnings_utc": 1593007200, "image_sprite_name": "GLXZ.png", "data_url": "/home/nima/Code/Earnbros/private/earnbros/v1/static/json/companies/GLXZ.json"}, {"market_cap": 1321680, "industry_name": "Metals and Mining", "sector_name": "Materials", "symbol": "AMNL", "name": "Applied Minerals", "next_earnings_utc": 1593007200, "image_sprite_name": "AMNL.png", "data_url": "/home/nima/Code/Earnbros/private/earnbros/v1/static/json/companies/AMNL.json"}, {"market_cap": 11675452, "industry_name": "Software", "sector_name": "Information Technology", "symbol": "VCSY", "name": "Vertical Computer Systems", "next_earnings_utc": 1593007200, "image_sprite_name": "VCSY.png", "data_url": "/home/nima/Code/Earnbros/private/earnbros/v1/static/json/companies/VCSY.json"}, {"market_cap": 2579868118, "industry_name": "Multiline Retail", "sector_name": "Consumer Discretionary", "symbol": "MAKSY", "name": "Marks & Spencer Group Plc ADR", "next_earnings_utc": 1593007200, "image_sprite_name": "MAKSY.png", "data_url": "/home/nima/Code/Earnbros/private/earnbros/v1/static/json/companies/MAKSY.json"}, {"market_cap": 76754676, "industry_name": "Health Care Equipment and Supplies", "sector_name": "Health Care", "symbol": "BWAY", "name": "Brainsway", "next_earnings_utc": 1593000000, "image_sprite_name": "BWAY.png", "data_url": "/home/nima/Code/Earnbros/private/earnbros/v1/static/json/companies/BWAY.json"}, {"market_cap": 9393587778, "industry_name": "Electric Utilities", "sector_name": "Utilities", "symbol": "EBR.B", "name": "Centrais El\u00e9tricas Brasileiras S.A. - Eletrobr\u00e1s", "next_earnings_utc": 1592992800, "image_sprite_name": "EBR.B.png", "data_url": "/home/nima/Code/Earnbros/private/earnbros/v1/static/json/companies/EBR.B.json"}, {"market_cap": 8532752, "industry_name": "Electronic Equipment, Instruments and Components", "sector_name": "Information Technology", "symbol": "ALPP", "name": "Alpine 4 Technologies", "next_earnings_utc": 1592992800, "image_sprite_name": "ALPP.png", "data_url": "/home/nima/Code/Earnbros/private/earnbros/v1/static/json/companies/ALPP.json"}, {"market_cap": 6351872, "industry_name": "Commercial Services and Supplies", "sector_name": "Industrials", "symbol": "SENR", "name": "Strategic Environmental & Energy Resources", "next_earnings_utc": 1593029100, "image_sprite_name": "SENR.png", "data_url": "/home/nima/Code/Earnbros/private/earnbros/v1/static/json/companies/SENR.json"}, {"market_cap": 29159960, "industry_name": "Electrical Equipment", "sector_name": "Industrials", "symbol": "ALPE", "name": "alpha-En", "next_earnings_utc": 1593007200, "image_sprite_name": "ALPE.png", "data_url": "/home/nima/Code/Earnbros/private/earnbros/v1/static/json/companies/ALPE.json"}, {"market_cap": 18092817, "industry_name": "Commercial Services and Supplies", "sector_name": "Industrials", "symbol": "BNET", "name": "Bion Environmental Technologies", "next_earnings_utc": 1593007200, "image_sprite_name": "BNET.png", "data_url": "/home/nima/Code/Earnbros/private/earnbros/v1/static/json/companies/BNET.json"}, {"market_cap": 10746570, "industry_name": "Chemicals", "sector_name": "Materials", "symbol": "ADMT", "name": "ADM Tronics Unlimited", "next_earnings_utc": 1593007200, "image_sprite_name": "ADMT.png", "data_url": "/home/nima/Code/Earnbros/private/earnbros/v1/static/json/companies/ADMT.json"}, {"market_cap": 243394116, "industry_name": "Independent Power and Renewable Electricity Producers", "sector_name": "Utilities", "symbol": "ELLO", "name": "Ellomay Capital", "next_earnings_utc": 1593032400, "image_sprite_name": "ELLO.png", "data_url": "/home/nima/Code/Earnbros/private/earnbros/v1/static/json/companies/ELLO.json"}, {"market_cap": 40590554134, "industry_name": "Construction Materials", "sector_name": "Materials", "symbol": "AHCHY", "name": "Anhui Conch Cement Company", "next_earnings_utc": 1593007200, "image_sprite_name": "AHCHY.png", "data_url": "/home/nima/Code/Earnbros/private/earnbros/v1/static/json/companies/AHCHY.json"}, {"market_cap": 5049583, "industry_name": "Oil, Gas and Consumable Fuels", "sector_name": "Energy", "symbol": "DWOG", "name": "Deep Well Oil & Gas", "next_earnings_utc": 1593007200, "image_sprite_name": "DWOG.png", "data_url": "/home/nima/Code/Earnbros/private/earnbros/v1/static/json/companies/DWOG.json"}, {"market_cap": 1320067, "industry_name": "Health Care Providers and Services", "sector_name": "Health Care", "symbol": "GRST", "name": "Ethema Health", "next_earnings_utc": 1593007200, "image_sprite_name": "GRST.png", "data_url": "/home/nima/Code/Earnbros/private/earnbros/v1/static/json/companies/GRST.json"}, {"market_cap": 37396273, "industry_name": "Specialty Retail", "sector_name": "Consumer Discretionary", "symbol": "KXIN", "name": "Kaixin Auto Holdings", "next_earnings_utc": 1593004500, "image_sprite_name": "KXIN.png", "data_url": "/home/nima/Code/Earnbros/private/earnbros/v1/static/json/companies/KXIN.json"}, {"market_cap": 201324096, "industry_name": "Internet and Direct Marketing Retail", "sector_name": "Consumer Discretionary", "symbol": "MKD", "name": "Molecular Data", "next_earnings_utc": 1593030600, "image_sprite_name": "MKD.png", "data_url": "/home/nima/Code/Earnbros/private/earnbros/v1/static/json/companies/MKD.json"}, {"market_cap": 65642500, "industry_name": "Banks", "sector_name": "Financials", "symbol": "JFBC", "name": "Jeffersonville Bancorp", "next_earnings_utc": 1593007200, "image_sprite_name": "JFBC.png", "data_url": "/home/nima/Code/Earnbros/private/earnbros/v1/static/json/companies/JFBC.json"}, {"market_cap": 2745951, "industry_name": "Software", "sector_name": "Information Technology", "symbol": "INTV", "name": "Integrated Ventures", "next_earnings_utc": 1593032400, "image_sprite_name": "INTV.png", "data_url": "/home/nima/Code/Earnbros/private/earnbros/v1/static/json/companies/INTV.json"}, {"market_cap": 5931825, "industry_name": "Health Care Technology", "sector_name": "Health Care", "symbol": "CMPD", "name": "CompuMed", "next_earnings_utc": 1592992800, "image_sprite_name": "CMPD.png", "data_url": "/home/nima/Code/Earnbros/private/earnbros/v1/static/json/companies/CMPD.json"}, {"market_cap": null, "industry_name": null, "sector_name": null, "symbol": "IGEN", "name": "iGen Networks", "next_earnings_utc": 1593030600, "image_sprite_name": "IGEN.png", "data_url": "/home/nima/Code/Earnbros/private/earnbros/v1/static/json/companies/IGEN.json"}, {"market_cap": 14048950, "industry_name": null, "sector_name": null, "symbol": "GMAN", "name": "Goldman Sachs ETF Trust - Goldman Sachs Motif Manufacturing Revolution ETF", "next_earnings_utc": 1592996400, "image_sprite_name": "GMAN.png", "data_url": "/home/nima/Code/Earnbros/private/earnbros/v1/static/json/companies/GMAN.json"}, {"market_cap": 433066499, "industry_name": "Machinery", "sector_name": "Industrials", "symbol": "IOCJY", "name": "Iochpe-Maxion", "next_earnings_utc": 1593030600, "image_sprite_name": "IOCJY.png", "data_url": "/home/nima/Code/Earnbros/private/earnbros/v1/static/json/companies/IOCJY.json"}, {"market_cap": 486566, "industry_name": "Auto Components", "sector_name": "Consumer Discretionary", "symbol": "PFTI", "name": "puraDYN Filter Technologies", "next_earnings_utc": 1592996700, "image_sprite_name": "PFTI.png", "data_url": "/home/nima/Code/Earnbros/private/earnbros/v1/static/json/companies/PFTI.json"}, {"market_cap": 135010, "industry_name": "Real Estate Management and Development", "sector_name": "Real Estate", "symbol": "AOXY", "name": "Advanced Oxygen Technologies", "next_earnings_utc": 1593007200, "image_sprite_name": "AOXY.png", "data_url": "/home/nima/Code/Earnbros/private/earnbros/v1/static/json/companies/AOXY.json"}]}