{"symbol": "BB", "name": "BlackBerry", "next_earnings_utc": 1593029100, "next_earnings_period_start_date_utc": 1582934400, "next_earnings_period_end_date_utc": 1590883200, "next_earnings_has_time": true, "next_earnings_name": "2021 Q1", "next_earnings_year": 2021, "next_earnings_quarter": 1, "next_earnings_revenue_num_analysts": null, "next_earnings_revenue_consensus": 218294290.0, "next_earnings_eps_num_analysts": null, "next_earnings_eps_consensus": -0.01444, "eps_up_revisions": 0, "eps_down_revisions": 6, "revenue_up_revisions": 0, "revenue_down_revisions": 4, "total_analysts": 13, "analysts_sell": 1, "analysts_buy": 1, "analysts_outperform": 1, "analysts_hold": 10, "analysts_underperform": 0, "webpage": "blackberry.com", "year_founded": 1984, "street_address": "2200 University Avenue East", "city": "Waterloo", "state": "ON", "zipcode": "N2K 0A7", "country": "Canada", "phone_number": "519 888 7465", "short_description": "BlackBerry Limited provides intelligent security software and services to enterprises and governments worldwide.", "long_description": "BlackBerry Limited provides intelligent security software and services to enterprises and governments worldwide. The company leverages artificial intelligence and machine learning to deliver solutions in the areas of cybersecurity; safety and data privacy; and endpoint security management, encryption, and embedded systems. It offers BlackBerry Spark software platform that includes a suite of security software products and services comprising BlackBerry Cylance, BlackBerry UEM, BlackBerry Dynamics, and BlackBerry Workspaces; and BlackBerry Spark SDK to promote the evolution of a platform ecosystem by enabling enterprise and independent software vendor developers to integrate the security features of BlackBerry Spark into their own mobile and web applications. BlackBerry Limited also provides BlackBerry Internet of Things (IoT) solutions, including BlackBerry QNX, BlackBerry AtHoc, SecuSUITE, BlackBerry Certicom, BlackBerry Radar, and other IoT applications; and manages and monetizes BlackBerry patents and applications. As of February 29, 2020, the company owned approximately 38,000 worldwide patents and applications. BlackBerry Limited has a partnership with the University of Windsor to develop and deliver a cybersecurity curriculum for the university's graduate master's program in applied computing. The company was formerly known as Research In Motion Limited and changed its name to BlackBerry Limited in July 2013. BlackBerry Limited was founded in 1984 and is headquartered in Waterloo, Canada.", "industry_name": "Software", "sector_name": "Information Technology", "is_defunct": false, "exchange": "NYSE", "equity_type": "stocks", "market_cap": 2917609575, "total_enterprise": 2768603330, "number_of_employees": 3658, "outstanding_shares": 555518584, "eps": -0.274437, "diluted_eps": -0.317402, "earnings_from_cont_operations": -152000000, "gross_profit": 768000000, "cash": 909000000, "total_debt": 758000000, "total_revenue": 1040000000, "cash_from_operations": 26000000, "net_income": -152000000, "ebitda": 43000000, "year_low_stock_price": 2.7, "year_high_stock_price": 9.09, "seekingalpha_follower_count": 135599, "image_url": "https://raw.githubusercontent.com/earnbros/earnbros.github.io/master/api/images/companies/BB.png"}