{"symbol": "CDEVY", "name": "City Developments", "next_earnings_utc": 1592316000, "next_earnings_period_start_date_utc": 1585612800, "next_earnings_period_end_date_utc": 1593475200, "next_earnings_has_time": true, "next_earnings_name": "2020 Q2", "next_earnings_year": 2020, "next_earnings_quarter": 2, "next_earnings_revenue_num_analysts": null, "next_earnings_revenue_consensus": 447448350.6730437, "next_earnings_eps_num_analysts": null, "next_earnings_eps_consensus": null, "eps_up_revisions": null, "eps_down_revisions": null, "revenue_up_revisions": 0, "revenue_down_revisions": 1, "total_analysts": 0, "analysts_sell": null, "analysts_buy": null, "analysts_outperform": null, "analysts_hold": null, "analysts_underperform": null, "webpage": "cdl.com.sg", "year_founded": 1963, "street_address": "9 Raffles Place", "city": "Singapore", "state": null, "zipcode": "048619", "country": "Singapore", "phone_number": "65 687 78228", "short_description": "City Developments Limited (CDL) is a leading global real estate operating company with a network spanning 103 locations in 29 countries and regions.", "long_description": "City Developments Limited (CDL) is a leading global real estate operating company with a network spanning 103 locations in 29 countries and regions. Listed on the Singapore Exchange, the Group is one of the largest companies by market capitalisation. Its income-stable and geographically-diverse portfolio comprises residences, offices, hotels, serviced apartments, integrated developments and shopping malls. With a proven track record of over 55 years in real estate development, investment and management, CDL has developed over 43,000 homes and owns over 18 million square feet of lettable floor area globally. Its diversified global land bank offers 4.1 million square feet of developable gross floor area. The Group's London-based hotel arm, Millennium & Copthorne Hotels (M&C), is one of the world's largest hotel chains, with over 145 hotels worldwide, many in key gateway cities. Leveraging its deep expertise in developing and managing a diversified asset base, the Group is focused on enhancing the performance of its portfolio and strengthening its recurring income streams to deliver long-term sustainable value to shareholders. The Group is also developing a fund management business and targets to achieve US$5 billion in Assets Under Management (AUM) by 2023.", "industry_name": "Real Estate Management and Development", "sector_name": "Real Estate", "is_defunct": false, "exchange": "Pink Current Info", "equity_type": "stocks", "market_cap": 5627001682, "total_enterprise": 11246479404, "number_of_employees": 15000, "outstanding_shares": 909301300, "eps": 0.452324440082092, "diluted_eps": 0.441021980309925, "earnings_from_cont_operations": 456084739, "gross_profit": 1218350138, "cash": 2504390857, "total_debt": 7542757503, "total_revenue": 2549541209, "cash_from_operations": 621923798, "net_income": 419809048, "ebitda": 596447161, "year_low_stock_price": 4.05, "year_high_stock_price": 8.56, "seekingalpha_follower_count": 52, "image_url": "https://raw.githubusercontent.com/earnbros/earnbros.github.io/master/api/images/companies/CDEVY.png"}