{"symbol": "CNAF", "name": "Commercial National Financial", "next_earnings_utc": 1595412000, "next_earnings_period_start_date_utc": null, "next_earnings_period_end_date_utc": null, "next_earnings_has_time": true, "next_earnings_name": "None QNone", "next_earnings_year": null, "next_earnings_quarter": null, "next_earnings_revenue_num_analysts": null, "next_earnings_revenue_consensus": null, "next_earnings_eps_num_analysts": null, "next_earnings_eps_consensus": null, "eps_up_revisions": null, "eps_down_revisions": null, "revenue_up_revisions": null, "revenue_down_revisions": null, "total_analysts": 0, "analysts_sell": null, "analysts_buy": null, "analysts_outperform": null, "analysts_hold": null, "analysts_underperform": null, "webpage": "cnbthebankonline.com", "year_founded": 1990, "street_address": "900 Ligonier Street", "city": "Latrobe", "state": "PA", "zipcode": "15650", "country": "United States", "phone_number": "724-539-3501", "short_description": "Commercial National Financial Corporation operates as a bank holding company for Commercial Bank & Trust of PA that provides various banking products and services in Pennsylvania.", "long_description": "Commercial National Financial Corporation operates as a bank holding company for Commercial Bank & Trust of PA that provides various banking products and services in Pennsylvania. The company offers checking, money market investment, and savings accounts; and business-time deposits, as well as certificates of deposit. It also provides loan products, such as home-equity, personal lines of credit, personal, and automobile loans, as well as residential and construction mortgages; and commercial loans, term loans, and lines of credit. In addition, the company offers other services, including automatic teller machine access/debit card, online banking, mobile banking, and online bill payment services; and direct deposit\\payroll processing and night depository services. Further, it provides asset management and trust services comprising trust and estate, investment management, and cash management services, as well as retirement products. The company operates a network of nine community offices with facilities in Greensburg, Hempfield Township, Latrobe, Ligonier, North Huntingdon, Unity Township, and West Newton. Commercial National Financial Corporation was founded in 1990 and is headquartered in Latrobe, Pennsylvania.", "industry_name": "Banks", "sector_name": "Financials", "is_defunct": false, "exchange": "OTC Markets", "equity_type": "stocks", "market_cap": 50954410, "total_enterprise": null, "number_of_employees": 98, "outstanding_shares": 2860953, "eps": 1.867909, "diluted_eps": 1.867909, "earnings_from_cont_operations": 5344000, "gross_profit": 18099000, "cash": 6206000, "total_debt": 25375000, "total_revenue": 18099000, "cash_from_operations": null, "net_income": 5344000, "ebitda": null, "year_low_stock_price": 15.26, "year_high_stock_price": 23.22, "seekingalpha_follower_count": 196, "image_url": "https://raw.githubusercontent.com/earnbros/earnbros.github.io/master/api/images/companies/CNAF.png"}