{"symbol": "DPW", "name": "DPW Holdings", "next_earnings_utc": 1591696800, "next_earnings_period_start_date_utc": 1585612800, "next_earnings_period_end_date_utc": null, "next_earnings_has_time": true, "next_earnings_name": "None QNone", "next_earnings_year": null, "next_earnings_quarter": null, "next_earnings_revenue_num_analysts": null, "next_earnings_revenue_consensus": null, "next_earnings_eps_num_analysts": null, "next_earnings_eps_consensus": null, "eps_up_revisions": null, "eps_down_revisions": null, "revenue_up_revisions": null, "revenue_down_revisions": null, "total_analysts": 0, "analysts_sell": null, "analysts_buy": null, "analysts_outperform": null, "analysts_hold": null, "analysts_underperform": null, "webpage": "dpwholdings.com", "year_founded": 1969, "street_address": "201 Shipyard Way", "city": "Newport Beach", "state": "CA", "zipcode": "92663", "country": "United States", "phone_number": "510-657-2635", "short_description": "DPW Holdings, Inc. designs, develops, manufactures, and sells power system solutions for the military/aerospace, medical, and industrial-telecommunication industries in North America and Europe.", "long_description": "DPW Holdings, Inc. designs, develops, manufactures, and sells power system solutions for the military/aerospace, medical, and industrial-telecommunication industries in North America and Europe. The company offers custom power system solutions; high-grade flexibility series power supply products, such as power rectifiers; and value-added services for original equipment manufacturers. It also provides power conversion and distribution equipment, direct current/active current inverters, and uninterrupted power supply products; and radio frequency and microwave filters, diplexers, multiplexers, detectors, switch filters, integrated assemblies, and detector logarithmic video amplifiers, as well as provides commercial loans. In addition, the company distributes value added power supply solutions, UPS systems, fans, filters, line cords, and other power-related components; manufactures specialized electronic systems for the military market; and owns and operates the Prep Kitchen brand restaurants located in the San Diego area. DPW Holdings, Inc. sells its products directly through its sales force, as well as through independent manufacturer representatives and distributors. The company was formerly known as Digital Power Corporation and changed its name to DPW Holdings, Inc. in December 2017. DPW Holdings, Inc. was founded in 1969 and is based in Newport Beach, California.", "industry_name": "Electrical Equipment", "sector_name": "Industrials", "is_defunct": false, "exchange": "NYSEMKT", "equity_type": "stocks", "market_cap": 6117932, "total_enterprise": 19825562, "number_of_employees": 247, "outstanding_shares": 5771634, "eps": -49.465184, "diluted_eps": -49.465184, "earnings_from_cont_operations": -33476107, "gross_profit": 5718078, "cash": 1229966, "total_debt": 14929222, "total_revenue": 25638389, "cash_from_operations": -9369627, "net_income": -32913865, "ebitda": -15572992, "year_low_stock_price": 0.53, "year_high_stock_price": 15.16, "seekingalpha_follower_count": 6201, "image_url": "https://raw.githubusercontent.com/earnbros/earnbros.github.io/master/api/images/companies/DPW.png"}