{"symbol": "ETCIA", "name": "Electronic Tele-Communications", "next_earnings_utc": 1592402400, "next_earnings_period_start_date_utc": null, "next_earnings_period_end_date_utc": null, "next_earnings_has_time": true, "next_earnings_name": "None QNone", "next_earnings_year": null, "next_earnings_quarter": null, "next_earnings_revenue_num_analysts": null, "next_earnings_revenue_consensus": null, "next_earnings_eps_num_analysts": null, "next_earnings_eps_consensus": null, "eps_up_revisions": null, "eps_down_revisions": null, "revenue_up_revisions": null, "revenue_down_revisions": null, "total_analysts": 0, "analysts_sell": null, "analysts_buy": null, "analysts_outperform": null, "analysts_hold": null, "analysts_underperform": null, "webpage": "etcia.com", "year_founded": 1980, "street_address": "1915 MacArthur Road", "city": "Waukesha", "state": "WI", "zipcode": "53188", "country": "United States", "phone_number": "262-542-5600", "short_description": "Electronic Tele-Communications, Inc. designs, manufactures, markets, leases, and sells digital voice information systems and related services to the telecommunications industry and other businesses.", "long_description": "Electronic Tele-Communications, Inc. designs, manufactures, markets, leases, and sells digital voice information systems and related services to the telecommunications industry and other businesses. Its equipment provides a range of audio and computer information, and call handling capabilities through telephone networks, computer networks, and the Internet. The company\u00e2\u20ac\u2122s digital voice information systems deliver network interoperability, as well as applications, including branding, time and temperature announcements, weather forecasts, automatic callback, changed number with call completion, repeat dialing, and wake-up/reminder services. It offers Digicept Emcee ELF3 and Digicept Emcee ELF that provide applications and services in a single platform for circuit and packet-switched networks; Audichron Z-10, a time-temperature-weather announcer; Audichron Z-10 MCA, a multi-channel announcer; digital announcement systems; and MAX Terminator, which offers disconnect detection to eliminate tied-up lines and annoying tones. The company also provides installation, repair, maintenance, and weather update services, as well as professional recording of announcements; and on-site training and technical support services. It serves regional bell operating companies, competitive local exchange carriers, independent telephone companies, long distance companies, wireless carriers, cable companies, utilities, telecommunications manufacturers, and other businesses and organizations. Electronic Tele-Communications, Inc. was incorporated in 1980 and is based in Waukesha, Wisconsin.", "industry_name": "Communications Equipment", "sector_name": "Information Technology", "is_defunct": false, "exchange": "Pink No Info", "equity_type": "stocks", "market_cap": 200731, "total_enterprise": 159350, "number_of_employees": 39, "outstanding_shares": 2509147, "eps": 0.00347, "diluted_eps": 0.00347, "earnings_from_cont_operations": 8709, "gross_profit": 259820, "cash": null, "total_debt": 0, "total_revenue": 527508, "cash_from_operations": null, "net_income": 8709, "ebitda": 32902, "year_low_stock_price": 0.01, "year_high_stock_price": 0.14, "seekingalpha_follower_count": 19, "image_url": "https://raw.githubusercontent.com/earnbros/earnbros.github.io/master/api/images/companies/ETCIA.png"}