{"symbol": "FCEL", "name": "FuelCell Energy", "next_earnings_utc": 1591959600, "next_earnings_period_start_date_utc": 1588204800, "next_earnings_period_end_date_utc": 1596153600, "next_earnings_has_time": true, "next_earnings_name": "2020 Q3", "next_earnings_year": 2020, "next_earnings_quarter": 3, "next_earnings_revenue_num_analysts": null, "next_earnings_revenue_consensus": 16046670.0, "next_earnings_eps_num_analysts": null, "next_earnings_eps_consensus": -0.06333, "eps_up_revisions": 2, "eps_down_revisions": 0, "revenue_up_revisions": 2, "revenue_down_revisions": 0, "total_analysts": 3, "analysts_sell": 1, "analysts_buy": 0, "analysts_outperform": 0, "analysts_hold": 2, "analysts_underperform": 0, "webpage": "fuelcellenergy.com", "year_founded": 1969, "street_address": "3 Great Pasture Road", "city": "Danbury", "state": "CT", "zipcode": "06810", "country": "United States", "phone_number": "203 825 6000", "short_description": "FuelCell Energy, Inc., together with its subsidiaries, designs, manufactures, sells, installs, operates, and services stationary fuel cell power plants for distributed power generation.", "long_description": "FuelCell Energy, Inc., together with its subsidiaries, designs, manufactures, sells, installs, operates, and services stationary fuel cell power plants for distributed power generation. The company offers SureSource product line based on carbonate fuel cell technology in various configurations, including on-site power, utility grid support, distributed hydrogen, and micro-grid, as well as multi-megawatt applications; and SureSource Recovery power plants for natural gas pipeline applications. It also provides SureSource Capture system that separates carbon dioxide from the flue gases of natural gas, biomass, or coal-fired power plants, as well as industrial facilities; and SOFC/SOEC and Energy Storage, a solution for energy storage using solid oxide technology. The company's SureSource power plants generate electricity and usable heat. It serves various markets, such as utilities and independent power producers, industrial and process applications, education and health care, data centers and communication, wastewater treatment, government, and commercial and hospitality. The company primarily operates in the United States, South Korea, England, and Germany. FuelCell Energy, Inc. was founded in 1969 and is headquartered in Danbury, Connecticut.", "industry_name": "Electrical Equipment", "sector_name": "Industrials", "is_defunct": false, "exchange": "NASDAQ", "equity_type": "stocks", "market_cap": 576188572, "total_enterprise": 825418572, "number_of_employees": 301, "outstanding_shares": 210968852, "eps": -0.657778, "diluted_eps": -0.657778, "earnings_from_cont_operations": -95410000, "gross_profit": 8324000, "cash": 29087000, "total_debt": 201049000, "total_revenue": 68897000, "cash_from_operations": -27094000, "net_income": -95410000, "ebitda": -13027000, "year_low_stock_price": 0.134, "year_high_stock_price": 3.42, "seekingalpha_follower_count": 38938, "image_url": "https://raw.githubusercontent.com/earnbros/earnbros.github.io/master/api/images/companies/FCEL.png"}