{"symbol": "IMH", "name": "Impac Mortgage Holdings", "next_earnings_utc": 1593115200, "next_earnings_period_start_date_utc": 1585612800, "next_earnings_period_end_date_utc": null, "next_earnings_has_time": true, "next_earnings_name": "None QNone", "next_earnings_year": null, "next_earnings_quarter": null, "next_earnings_revenue_num_analysts": null, "next_earnings_revenue_consensus": null, "next_earnings_eps_num_analysts": null, "next_earnings_eps_consensus": null, "eps_up_revisions": null, "eps_down_revisions": null, "revenue_up_revisions": null, "revenue_down_revisions": null, "total_analysts": 0, "analysts_sell": null, "analysts_buy": null, "analysts_outperform": null, "analysts_hold": null, "analysts_underperform": null, "webpage": "impaccompanies.com", "year_founded": 1995, "street_address": "19500 Jamboree Road", "city": "Irvine", "state": "CA", "zipcode": "92612", "country": "United States", "phone_number": "949-475-3600", "short_description": "Impac Mortgage Holdings, Inc. operates as an independent residential mortgage lender in the United States.", "long_description": "Impac Mortgage Holdings, Inc. operates as an independent residential mortgage lender in the United States. It operates through three segments: Mortgage Lending, Real Estate Services, and Long-Term Mortgage Portfolio. The Mortgage Lending segment provides mortgage lending products through three lending channels, such as retail, wholesale, and correspondent and opportunistically retain mortgage servicing rights. The Real Estate Services segment provides loss mitigation and real estate services primarily on its long-term mortgage portfolio, including default surveillance, loan modification, short sale, and real estate owned surveillance and disposition services, as well as monitoring, reconciling, and reporting services for residential and multifamily mortgage portfolios. This segment provides services to investors, servicers, and individual borrowers primarily focusing on loss mitigation and performance. The Long-Term Mortgage Portfolio segment consists of residual interests in the securitization trusts reflected as trust assets and liabilities in its consolidated balance sheets. Impac Mortgage Holdings, Inc. was founded in 1995 and is headquartered in Irvine, California.", "industry_name": "Thrifts and Mortgage Finance", "sector_name": "Financials", "is_defunct": false, "exchange": "NYSEMKT", "equity_type": "stocks", "market_cap": 42104553, "total_enterprise": null, "number_of_employees": 530, "outstanding_shares": 21264926, "eps": -0.376468, "diluted_eps": -0.38, "earnings_from_cont_operations": -7977000, "gross_profit": -40329000, "cash": 32457000, "total_debt": 3412436000, "total_revenue": -40329000, "cash_from_operations": -377483000, "net_income": -7977000, "ebitda": null, "year_low_stock_price": 1.31, "year_high_stock_price": 8.03, "seekingalpha_follower_count": 1541, "image_url": "https://raw.githubusercontent.com/earnbros/earnbros.github.io/master/api/images/companies/IMH.png"}