{"symbol": "ULTR", "name": "IndexIQ Active ETF Trust - IQ Ultra Short Duration ETF", "next_earnings_utc": 1592597700, "next_earnings_period_start_date_utc": null, "next_earnings_period_end_date_utc": null, "next_earnings_has_time": true, "next_earnings_name": "None QNone", "next_earnings_year": null, "next_earnings_quarter": null, "next_earnings_revenue_num_analysts": null, "next_earnings_revenue_consensus": null, "next_earnings_eps_num_analysts": null, "next_earnings_eps_consensus": null, "eps_up_revisions": null, "eps_down_revisions": null, "revenue_up_revisions": null, "revenue_down_revisions": null, "total_analysts": 0, "analysts_sell": null, "analysts_buy": null, "analysts_outperform": null, "analysts_hold": null, "analysts_underperform": null, "webpage": "nylinvestments.com", "year_founded": 2019, "street_address": "800 Westchester Avenue", "city": "Rye Brook", "state": "NY", "zipcode": "10573", "country": "United States", "phone_number": "888-934-0777", "short_description": "IndexIQ Active ETF Trust - IQ Ultra Short Duration ETF is an exchange traded fund launched by New York Life Investment Management LLC. It is co-managed by IndexIQ Advisors LLC and NYL Investors LLC. The fund invests in fixed income markets across the globe.", "long_description": "IndexIQ Active ETF Trust - IQ Ultra Short Duration ETF is an exchange traded fund launched by New York Life Investment Management LLC. It is co-managed by IndexIQ Advisors LLC and NYL Investors LLC. The fund invests in fixed income markets across the globe. It invests directly and through other funds in fixed income securities including U.S. Government securities  like Treasury notes, obligations, repurchase agreements, agency securities, corporate bonds, instruments of non-U.S. issuers, asset-backed securities, mortgage-backed securities, commercial mortgage-backed securities, commercial paper, debentures, floating rate bonds, and convertible corporate bonds rated by BBB- or higher by S&P or Fitch or Baa3 or higher by Moody\u00e2\u20ac\u2122s. The fund invests in securities with an average duration of 1 year or less. IndexIQ Active ETF Trust - IQ Ultra Short Duration ETF was formed on July 31, 2019 and is domiciled in the United States.", "industry_name": null, "sector_name": null, "is_defunct": false, "exchange": "NYSEARCA", "equity_type": "etf", "market_cap": 162772500, "total_enterprise": null, "number_of_employees": null, "outstanding_shares": null, "eps": null, "diluted_eps": null, "earnings_from_cont_operations": null, "gross_profit": null, "cash": null, "total_debt": null, "total_revenue": null, "cash_from_operations": null, "net_income": null, "ebitda": null, "year_low_stock_price": 47.63, "year_high_stock_price": 53.12, "seekingalpha_follower_count": 773, "image_url": "https://raw.githubusercontent.com/earnbros/earnbros.github.io/master/api/images/companies/ULTR.png"}