{"symbol": "UUU", "name": "Universal Security Instruments", "next_earnings_utc": 1591794000, "next_earnings_period_start_date_utc": null, "next_earnings_period_end_date_utc": null, "next_earnings_has_time": true, "next_earnings_name": "None QNone", "next_earnings_year": null, "next_earnings_quarter": null, "next_earnings_revenue_num_analysts": null, "next_earnings_revenue_consensus": null, "next_earnings_eps_num_analysts": null, "next_earnings_eps_consensus": null, "eps_up_revisions": null, "eps_down_revisions": null, "revenue_up_revisions": null, "revenue_down_revisions": null, "total_analysts": 0, "analysts_sell": null, "analysts_buy": null, "analysts_outperform": null, "analysts_hold": null, "analysts_underperform": null, "webpage": "universalsecurity.com", "year_founded": 1969, "street_address": "11407 Cronhill Drive", "city": "Owings Mills", "state": "MD", "zipcode": "21117", "country": "United States", "phone_number": "410-363-3000", "short_description": "Universal Security Instruments, Inc., together with its subsidiary, designs, markets, and distributes safety and security products for use in homes and businesses in the United States and internationally.", "long_description": "Universal Security Instruments, Inc., together with its subsidiary, designs, markets, and distributes safety and security products for use in homes and businesses in the United States and internationally. The company offers a line of safety alarms, including units powered by replaceable batteries, sealed batteries, and electrical batteries with battery backup alarms; and smoke alarms, which include hearing impaired and heat alarms, as well as carbon monoxide alarms, door chimes, ventilation products, ground fault circuit interrupters, and other electrical devices. It provides its products to wholesale distributors; chain, discount, and television retailers; home center stores; catalog and mail order companies; electrical and lighting distributors, and manufactured housing companies; and other distributors. It also sells its products through approximately 40 independent sales organizations and 100 sales representatives, as well as through its own sales catalogs and brochures, and Website. Universal Security Instruments, Inc. was founded in 1969 and is headquartered in Owings Mills, Maryland.", "industry_name": "Electronic Equipment, Instruments and Components", "sector_name": "Information Technology", "is_defunct": false, "exchange": "NYSEMKT", "equity_type": "stocks", "market_cap": 1401609, "total_enterprise": 8552321, "number_of_employees": 13, "outstanding_shares": 2312887, "eps": -1.120866, "diluted_eps": -1.120866, "earnings_from_cont_operations": -2592437, "gross_profit": 4901384, "cash": 177337, "total_debt": 7328049, "total_revenue": 15713168, "cash_from_operations": 216040, "net_income": -2592437, "ebitda": -624146, "year_low_stock_price": 0.3011, "year_high_stock_price": 1.33, "seekingalpha_follower_count": 702, "image_url": "https://raw.githubusercontent.com/earnbros/earnbros.github.io/master/api/images/companies/UUU.png"}